.hgignore
CHANGES.txt
LICENSE.txt
README.txt
bootstrap.py
buildout.cfg
setup.py
src/sw/__init__.py
src/sw.nikeplus.egg-info/PKG-INFO
src/sw.nikeplus.egg-info/SOURCES.txt
src/sw.nikeplus.egg-info/dependency_links.txt
src/sw.nikeplus.egg-info/namespace_packages.txt
src/sw.nikeplus.egg-info/requires.txt
src/sw.nikeplus.egg-info/top_level.txt
src/sw.nikeplus.egg-info/zip-safe
src/sw/nikeplus/__init__.py
src/sw/nikeplus/fetcher.py
src/sw/nikeplus/nikeplus.txt
src/sw/nikeplus/testing.py
src/sw/nikeplus/utils.py
src/sw/nikeplus/tests/__init__.py
src/sw/nikeplus/tests/test_doctest.py
src/sw/nikeplus/tests/test_fetcher.py
src/sw/nikeplus/tests/test_xml2json.py