Metadata-Version: 1.0
Name: sw.nikeplus
Version: 0.1
Summary: API for retrieving workout data from Nike+.
Home-page: https://bitbucket.org/sweh/sw.nikeplus
Author: Sebastian Wehrmann
Author-email: sebastian.wehrmann@me.com
License: ZPL 2.1
Platform: UNKNOWN
Classifier: Intended Audience :: Developers
Classifier: License :: OSI Approved :: Zope Public License
Classifier: Programming Language :: Python
Classifier: Natural Language :: English
Classifier: Operating System :: OS Independent
